{
    "CompRank": 283,
    "CompositeDef": 107.0416409902654,
    "CompositeOff": 96.72687533939133,
    "CompositePace": 68.35877990285144,
    "CompositeRating": -10.31476565087408,
    "HA": [
        "A",
        "A",
        "A",
        "A",
        "A",
        "A",
        "A",
        "N",
        "N",
        "H",
        "A",
        "A",
        "H",
        "H",
        "A",
        "A",
        "H",
        "H",
        "A",
        "A",
        "A",
        "H",
        "H",
        "A",
        "A",
        "H",
        "H",
        "H",
        "N",
        "N",
        "N"
    ],
    "OAst": 395.0,
    "OAvgCompRat": -6.028706256407925,
    "OBlk": 102.0,
    "ODR": 762.0,
    "OFGA": 1753.0,
    "OFGA3": 632.0,
    "OFGM": 742.0,
    "OFGM3": 205.0,
    "OFTA": 709.0,
    "OFTM": 503.0,
    "OOR": 312.0,
    "OPF": 467.0,
    "OScore": 2192.0,
    "OStl": 210.0,
    "OTO": 380.0,
    "Oastr": 0.13908646600656346,
    "Ocomprank": 336,
    "Ocorrdastr": 0.15801146245377704,
    "Ocorrdeff": 108.10680768392943,
    "Ocorrdeffrank": 302,
    "Ocorrdefgp": 0.5310128479488363,
    "Ocorrdftr": 0.36655250707541354,
    "Ocorrdorbp": 0.30497318027093356,
    "Ocorrdtovr": 0.1562442249822737,
    "Ocorroastr": 0.13007873895060307,
    "Ocorroeff": 101.21211583299049,
    "Ocorroeffrank": 323,
    "Ocorroefgp": 0.4779831942184514,
    "Ocorroftr": 0.32984316434777405,
    "Ocorroorbp": 0.2636782144118415,
    "Ocorrotovr": 0.1506138480503349,
    "Oeff": 102.76798439726952,
    "Oefgp": 0.4817455790074159,
    "Oftr": 0.4044495151169424,
    "Oneteff": -6.8946918509389405,
    "Oneteffrank": 327,
    "Oorbp": 0.29913710450623204,
    "Oposs": 2132.96,
    "Otovr": 0.15542176559125712,
    "SoR": 0.0,
    "SoRrank": 129,
    "TAst": 348.0,
    "TBlk": 112.0,
    "TDR": 731.0,
    "TFGA": 1834.0,
    "TFGA3": 714.0,
    "TFGM": 749.0,
    "TFGM3": 222.0,
    "TFTA": 578.0,
    "TFTM": 417.0,
    "TOR": 320.0,
    "TPF": 512.0,
    "TScore": 2137.0,
    "TStl": 209.0,
    "TTO": 386.0,
    "Tastr": 0.12330281470563224,
    "Tcorrdastr": 0.15287592057021626,
    "Tcorrdastrrank": 259,
    "Tcorrdeff": 107.0416409902654,
    "Tcorrdeffrank": 203,
    "Tcorrdefgp": 0.5094128750774273,
    "Tcorrdefgprank": 185,
    "Tcorrdftr": 0.4058815788074564,
    "Tcorrdftrrank": 321,
    "Tcorrdorbp": 0.3168999423154683,
    "Tcorrdorbprank": 317,
    "Tcorrdtovr": 0.15216820988426455,
    "Tcorrdtovrrank": 140,
    "Tcorroastr": 0.11164091051600324,
    "Tcorroastrrank": 344,
    "Tcorroeff": 96.72687533939133,
    "Tcorroeffrank": 309,
    "Tcorroefgp": 0.4463923148849853,
    "Tcorroefgprank": 341,
    "Tcorroftr": 0.28538598407877047,
    "Tcorroftrrank": 298,
    "Tcorroorbp": 0.27154108029439156,
    "Tcorroorbprank": 192,
    "Tcorrotovr": 0.14724252750486305,
    "Tcorrotovrrank": 181,
    "Teff": 99.19603401537375,
    "Tefgp": 0.46892039258451473,
    "Tftr": 0.31515812431842966,
    "Tneteff": -10.31476565087408,
    "Tneteffrank": 283,
    "Torbp": 0.2957486136783734,
    "Tposs": 2154.32,
    "Ttovr": 0.15600245724077724,
    "closses": 6,
    "confplace": 3,
    "cwins": 12,
    "dates": [
        [
            11,
            6
        ],
        [
            11,
            11
        ],
        [
            11,
            16
        ],
        [
            11,
            18
        ],
        [
            11,
            21
        ],
        [
            11,
            25
        ],
        [
            11,
            28
        ],
        [
            12,
            16
        ],
        [
            12,
            17
        ],
        [
            12,
            21
        ],
        [
            1,
            6
        ],
        [
            1,
            8
        ],
        [
            1,
            13
        ],
        [
            1,
            15
        ],
        [
            1,
            20
        ],
        [
            1,
            22
        ],
        [
            1,
            27
        ],
        [
            1,
            29
        ],
        [
            2,
            3
        ],
        [
            2,
            10
        ],
        [
            2,
            12
        ],
        [
            2,
            17
        ],
        [
            2,
            19
        ],
        [
            2,
            24
        ],
        [
            2,
            26
        ],
        [
            3,
            2
        ],
        [
            3,
            4
        ],
        [
            3,
            9
        ],
        [
            3,
            14
        ],
        [
            3,
            15
        ],
        [
            3,
            16
        ]
    ],
    "geff": [
        [
            70.18887187340479,
            118.13045711350797
        ],
        [
            67.46237675142709,
            88.334268087493
        ],
        [
            52.51432208784214,
            104.65901417960836
        ],
        [
            76.17306520414381,
            125.61274509803921
        ],
        [
            96.15384615384616,
            105.72543916720885
        ],
        [
            108.0340839926963,
            120.08733624454148
        ],
        [
            88.20431806213797,
            132.70777479892763
        ],
        [
            115.90375586854461,
            124.85311398354877
        ],
        [
            111.77136389360497,
            110.73253833049404
        ],
        [
            83.63355635615028,
            111.99794026776519
        ],
        [
            69.40664126292869,
            82.62108262108262
        ],
        [
            87.66233766233766,
            80.19740900678593
        ],
        [
            98.35584263065178,
            104.66507177033493
        ],
        [
            143.2532347504621,
            90.55819477434679
        ],
        [
            105.14018691588784,
            94.77936606587943
        ],
        [
            87.67123287671232,
            98.64864864864865
        ],
        [
            115.67773543821447,
            96.04677060133629
        ],
        [
            91.62303664921467,
            86.15288220551378
        ],
        [
            107.93308148947652,
            97.67836919592298
        ],
        [
            99.43906170321264,
            96.64948453608248
        ],
        [
            113.63636363636364,
            119.18437679494544
        ],
        [
            97.22222222222223,
            100.91743119266054
        ],
        [
            103.65853658536587,
            86.0479409956976
        ],
        [
            105.36951501154734,
            78.64488808227465
        ],
        [
            110.63218390804599,
            102.51903925014645
        ],
        [
            113.63636363636363,
            105.8681185722928
        ],
        [
            119.1913095956548,
            111.83851609383525
        ],
        [
            120.4039357845676,
            101.5625
        ],
        [
            114.6356783919598,
            96.03469640644362
        ],
        [
            101.69491525423729,
            89.87831858407081
        ],
        [
            105.29674537332482,
            117.85040854808297
        ]
    ],
    "losses": 16,
    "nOT": [
        0,
        0,
        0,
        0,
        0,
        0,
        0,
        0,
        0,
        0,
        0,
        0,
        0,
        0,
        0,
        0,
        0,
        0,
        0,
        1,
        0,
        0,
        0,
        0,
        0,
        0,
        0,
        0,
        0,
        0,
        0
    ],
    "pace": 68.35877990285144,
    "poss": [
        [
            78.36,
            77.88
        ],
        [
            77.08,
            71.32
        ],
        [
            62.84,
            59.24
        ],
        [
            65.64,
            65.28
        ],
        [
            65.52,
            61.480000000000004
        ],
        [
            65.72,
            64.12
        ],
        [
            75.96,
            74.6
        ],
        [
            68.16,
            68.08
        ],
        [
            70.68,
            70.44
        ],
        [
            77.72,
            77.68
        ],
        [
            73.48,
            70.2
        ],
        [
            61.6,
            64.84
        ],
        [
            68.12,
            66.88
        ],
        [
            64.92,
            67.36
        ],
        [
            68.48,
            64.36
        ],
        [
            73.0,
            74.0
        ],
        [
            73.48,
            71.84
        ],
        [
            61.12,
            63.84
        ],
        [
            74.12,
            70.64
        ],
        [
            78.44,
            77.6
        ],
        [
            69.52,
            69.64
        ],
        [
            64.8,
            65.4
        ],
        [
            65.6,
            65.08
        ],
        [
            69.28,
            66.12
        ],
        [
            69.6,
            68.28
        ],
        [
            70.4,
            66.12
        ],
        [
            66.28,
            73.32
        ],
        [
            77.24,
            76.8
        ],
        [
            63.68,
            64.56
        ],
        [
            70.8,
            72.32
        ],
        [
            62.68,
            63.64
        ]
    ],
    "preseason_pace": 69.36444399893227,
    "preseason_pred": -9.898157976568008,
    "preseason_predd": 104.96770646028465,
    "preseason_predo": 95.06954848371664,
    "schedule": [
        "new-mexico",
        "arizona-state",
        "virginia",
        "creighton",
        "oral-roberts",
        "drake",
        "purdue",
        "north-carolina-at",
        "howard",
        "samford",
        "southern",
        "grambling",
        "arkansas-pine-bluff",
        "mississippi-valley-state",
        "alcorn-state",
        "jackson-state",
        "alabama-am",
        "alabama-state",
        "prairie-view",
        "florida-am",
        "bethune-cookman",
        "grambling",
        "southern",
        "mississippi-valley-state",
        "arkansas-pine-bluff",
        "jackson-state",
        "alcorn-state",
        "prairie-view",
        "jackson-state",
        "alabama-am",
        "grambling"
    ],
    "scores": [
        [
            55,
            92
        ],
        [
            52,
            63
        ],
        [
            33,
            62
        ],
        [
            50,
            82
        ],
        [
            63,
            65
        ],
        [
            71,
            77
        ],
        [
            67,
            99
        ],
        [
            79,
            85
        ],
        [
            79,
            78
        ],
        [
            65,
            87
        ],
        [
            51,
            58
        ],
        [
            54,
            52
        ],
        [
            67,
            70
        ],
        [
            93,
            61
        ],
        [
            72,
            61
        ],
        [
            64,
            73
        ],
        [
            85,
            69
        ],
        [
            56,
            55
        ],
        [
            80,
            69
        ],
        [
            78,
            75
        ],
        [
            79,
            83
        ],
        [
            63,
            66
        ],
        [
            68,
            56
        ],
        [
            73,
            52
        ],
        [
            77,
            70
        ],
        [
            80,
            70
        ],
        [
            79,
            82
        ],
        [
            93,
            78
        ],
        [
            73,
            62
        ],
        [
            72,
            65
        ],
        [
            66,
            75
        ]
    ],
    "wins": 15
}