{
    "CompRank": 53,
    "CompositeDef": 108.94527301979623,
    "CompositeOff": 124.78608546111296,
    "CompositePace": 69.0792092802328,
    "CompositeRating": 15.840812441316725,
    "HA": [
        "N",
        "A",
        "A",
        "H",
        "N",
        "N",
        "H",
        "H",
        "N",
        "A",
        "H",
        "H",
        "A",
        "H",
        "A",
        "A",
        "H",
        "A",
        "H",
        "H"
    ],
    "OAst": 254.0,
    "OAvgCompRat": -1.0645424335283427,
    "OBlk": 56.0,
    "ODR": 413.0,
    "OFGA": 1183.0,
    "OFGA3": 470.0,
    "OFGM": 515.0,
    "OFGM3": 164.0,
    "OFTA": 387.0,
    "OFTM": 280.0,
    "OOR": 202.0,
    "OPF": 276.0,
    "OScore": 1476.0,
    "OStl": 123.0,
    "OTO": 221.0,
    "Oastr": 0.13892839171242918,
    "Ocomprank": 199,
    "Ocorrdastr": 0.14261541315140502,
    "Ocorrdeff": 108.78181184558696,
    "Ocorrdeffrank": 171,
    "Ocorrdefgp": 0.5082525400186979,
    "Ocorrdftr": 0.3881330058245635,
    "Ocorrdorbp": 0.31113271774093804,
    "Ocorrdtovr": 0.15494134375330157,
    "Ocorroastr": 0.13743707934650481,
    "Ocorroeff": 107.37920873978541,
    "Ocorroeffrank": 251,
    "Ocorroefgp": 0.49827639048913464,
    "Ocorroftr": 0.36405619297573105,
    "Ocorroorbp": 0.323128504516499,
    "Ocorrotovr": 0.14393458385126678,
    "Oeff": 107.5582242690996,
    "Oefgp": 0.5046491969568893,
    "Oftr": 0.32713440405748095,
    "Oneteff": -1.4026031058015462,
    "Oneteffrank": 211,
    "Oorbp": 0.2849083215796897,
    "Oposs": 1372.28,
    "Otovr": 0.14038163477907362,
    "SoR": 24.91181847169304,
    "SoRrank": 54,
    "TAst": 301.0,
    "TBlk": 47.0,
    "TDR": 507.0,
    "TFGA": 1132.0,
    "TFGA3": 495.0,
    "TFGM": 558.0,
    "TFGM3": 202.0,
    "TFTA": 508.0,
    "TFTM": 405.0,
    "TOR": 199.0,
    "TPF": 284.0,
    "TScore": 1723.0,
    "TStl": 135.0,
    "TTO": 214.0,
    "Tastr": 0.16091781964373544,
    "Tcorrdastr": 0.14941978611287618,
    "Tcorrdastrrank": 194,
    "Tcorrdeff": 109.04759833150126,
    "Tcorrdeffrank": 172,
    "Tcorrdefgp": 0.5202135359222066,
    "Tcorrdefgprank": 206,
    "Tcorrdftr": 0.3203157397262883,
    "Tcorrdftrrank": 97,
    "Tcorrdorbp": 0.26830780705258794,
    "Tcorrdorbprank": 62,
    "Tcorrdtovr": 0.144566174998678,
    "Tcorrdtovrrank": 200,
    "Tcorroastr": 0.16692184231002372,
    "Tcorroastrrank": 67,
    "Tcorroeff": 125.87838505630526,
    "Tcorroeffrank": 16,
    "Tcorroefgp": 0.5888087785959066,
    "Tcorroefgprank": 17,
    "Tcorroftr": 0.4132902451556011,
    "Tcorroftrrank": 54,
    "Tcorroorbp": 0.31892123853681065,
    "Tcorroorbprank": 139,
    "Tcorrotovr": 0.13033500768097006,
    "Tcorrotovrrank": 66,
    "Teff": 125.71870530893383,
    "Tefgp": 0.5821554770318021,
    "Tftr": 0.44876325088339225,
    "Tneteff": 16.830786724804,
    "Tneteffrank": 50,
    "Torbp": 0.32516339869281047,
    "Tposs": 1370.52,
    "Ttovr": 0.1363474183189765,
    "closses": 2,
    "confplace": 1,
    "cwins": 7,
    "dates": [
        [
            11,
            7
        ],
        [
            11,
            12
        ],
        [
            11,
            17
        ],
        [
            11,
            21
        ],
        [
            11,
            25
        ],
        [
            11,
            26
        ],
        [
            12,
            6
        ],
        [
            12,
            10
        ],
        [
            12,
            13
        ],
        [
            12,
            19
        ],
        [
            12,
            22
        ],
        [
            12,
            31
        ],
        [
            1,
            4
        ],
        [
            1,
            10
        ],
        [
            1,
            14
        ],
        [
            1,
            18
        ],
        [
            1,
            21
        ],
        [
            1,
            24
        ],
        [
            1,
            28
        ],
        [
            2,
            1
        ]
    ],
    "geff": [
        [
            117.8838412880966,
            100.99440646364201
        ],
        [
            120.81274025260845,
            117.88617886178862
        ],
        [
            112.52711496746203,
            111.6427432216906
        ],
        [
            121.6685979142526,
            110.22927689594356
        ],
        [
            131.92182410423453,
            84.43708609271523
        ],
        [
            102.27272727272727,
            94.63722397476342
        ],
        [
            148.03625377643505,
            111.51295961422544
        ],
        [
            149.46346448645886,
            113.14655172413794
        ],
        [
            123.1454005934718,
            99.37535491198183
        ],
        [
            117.00913242009133,
            116.44623346751005
        ],
        [
            119.11064055055584,
            111.19832548403977
        ],
        [
            150.9023024268824,
            74.44168734491315
        ],
        [
            108.06451612903226,
            118.18778726198292
        ],
        [
            108.09312638580931,
            128.5240464344942
        ],
        [
            128.9742051589682,
            113.01160659743432
        ],
        [
            136.7403314917127,
            110.50516647531572
        ],
        [
            130.0125313283208,
            99.75816203143894
        ],
        [
            133.19044703000614,
            122.4304715840387
        ],
        [
            120.16412661195781,
            92.07589285714285
        ],
        [
            133.08528906697197,
            113.57416529830323
        ]
    ],
    "losses": 3,
    "nOT": [
        0,
        0,
        0,
        0,
        0,
        0,
        0,
        0,
        0,
        0,
        0,
        0,
        0,
        0,
        0,
        0,
        0,
        0,
        0,
        0
    ],
    "pace": 69.12380335669356,
    "poss": [
        [
            69.56,
            64.36
        ],
        [
            72.84,
            73.8
        ],
        [
            73.76,
            75.24
        ],
        [
            69.04,
            68.04
        ],
        [
            61.4,
            60.4
        ],
        [
            61.6,
            63.4
        ],
        [
            66.2,
            66.36
        ],
        [
            78.28,
            74.24
        ],
        [
            67.4,
            70.44
        ],
        [
            70.08,
            69.56
        ],
        [
            75.56,
            76.44
        ],
        [
            64.28,
            64.48
        ],
        [
            62.0,
            60.92
        ],
        [
            72.16,
            72.36
        ],
        [
            66.68,
            65.48
        ],
        [
            72.4,
            69.68
        ],
        [
            63.84,
            66.16
        ],
        [
            65.32,
            66.16
        ],
        [
            68.24,
            71.68
        ],
        [
            69.88,
            73.08
        ]
    ],
    "preseason_pace": 68.19698980091758,
    "preseason_pred": -3.7441788003398084,
    "preseason_predd": 106.92093726989859,
    "preseason_predo": 103.17675846955879,
    "schedule": [
        "rhode-island",
        "oral-roberts",
        "kansas-state",
        "austin-peay",
        "san-jose-state",
        "northern-iowa",
        "missouri-state",
        "arkansas-pine-bluff",
        "new-mexico-state",
        "western-kentucky",
        "denver",
        "rice",
        "north-texas",
        "south-florida",
        "charlotte",
        "alabama-birmingham",
        "memphis",
        "rice",
        "north-texas",
        "wichita-state"
    ],
    "scores": [
        [
            82,
            65
        ],
        [
            88,
            87
        ],
        [
            83,
            84
        ],
        [
            84,
            75
        ],
        [
            81,
            51
        ],
        [
            63,
            60
        ],
        [
            98,
            74
        ],
        [
            117,
            84
        ],
        [
            83,
            70
        ],
        [
            82,
            81
        ],
        [
            90,
            85
        ],
        [
            97,
            48
        ],
        [
            67,
            72
        ],
        [
            78,
            93
        ],
        [
            86,
            74
        ],
        [
            99,
            77
        ],
        [
            83,
            66
        ],
        [
            87,
            81
        ],
        [
            82,
            66
        ],
        [
            93,
            83
        ]
    ],
    "wins": 17
}