{
    "CompRank": 241,
    "CompositeDef": 108.01915755874951,
    "CompositeOff": 101.44935750945355,
    "CompositePace": 70.82297407129701,
    "CompositeRating": -6.569800049295964,
    "HA": [
        "A",
        "H",
        "H",
        "N",
        "N",
        "A",
        "A",
        "A",
        "A",
        "A",
        "H",
        "A",
        "H",
        "H",
        "A",
        "A",
        "H",
        "H"
    ],
    "OAst": 277.0,
    "OAvgCompRat": -6.274898907452419,
    "OBlk": 67.0,
    "ODR": 432.0,
    "OFGA": 976.0,
    "OFGA3": 400.0,
    "OFGM": 473.0,
    "OFGM3": 144.0,
    "OFTA": 394.0,
    "OFTM": 255.0,
    "OOR": 146.0,
    "OPF": 325.0,
    "OScore": 1345.0,
    "OStl": 114.0,
    "OTO": 287.0,
    "Oastr": 0.16167063547649063,
    "Ocomprank": 351,
    "Ocorrdastr": 0.15765667169513423,
    "Ocorrdeff": 105.47709556567548,
    "Ocorrdeffrank": 339,
    "Ocorrdefgp": 0.5259461962819112,
    "Ocorrdftr": 0.3604757147792679,
    "Ocorrdorbp": 0.28961219887856604,
    "Ocorrdtovr": 0.16711369314628852,
    "Ocorroastr": 0.13176027986009056,
    "Ocorroeff": 98.15706637113145,
    "Ocorroeffrank": 349,
    "Ocorroefgp": 0.4777456936442076,
    "Ocorroftr": 0.32011736812323377,
    "Ocorroorbp": 0.28152782150673633,
    "Ocorrotovr": 0.1645472620707167,
    "Oeff": 104.23447720016118,
    "Oefgp": 0.5584016393442623,
    "Oftr": 0.4036885245901639,
    "Oneteff": -7.320029194544034,
    "Oneteffrank": 349,
    "Oorbp": 0.2718808193668529,
    "Oposs": 1290.3600000000001,
    "Otovr": 0.19981063243198083,
    "SoR": 0.0,
    "SoRrank": 166,
    "TAst": 274.0,
    "TBlk": 22.0,
    "TDR": 391.0,
    "TFGA": 1101.0,
    "TFGA3": 419.0,
    "TFGM": 479.0,
    "TFGM3": 153.0,
    "TFTA": 345.0,
    "TFTM": 272.0,
    "TOR": 168.0,
    "TPF": 355.0,
    "TScore": 1383.0,
    "TStl": 160.0,
    "TTO": 227.0,
    "Tastr": 0.15623218154863724,
    "Tcorrdastr": 0.17530965788352654,
    "Tcorrdastrrank": 347,
    "Tcorrdeff": 108.41141376281963,
    "Tcorrdeffrank": 289,
    "Tcorrdefgp": 0.5884959211551277,
    "Tcorrdefgprank": 360,
    "Tcorrdftr": 0.39933379485354675,
    "Tcorrdftrrank": 328,
    "Tcorrdorbp": 0.2591316938854394,
    "Tcorrdorbprank": 151,
    "Tcorrdtovr": 0.19308148937129255,
    "Tcorrdtovrrank": 29,
    "Tcorroastr": 0.14146886666431044,
    "Tcorroastrrank": 174,
    "Tcorroeff": 102.0542745707275,
    "Tcorroeffrank": 179,
    "Tcorroefgp": 0.48309787832756657,
    "Tcorroefgprank": 262,
    "Tcorroftr": 0.2762323010136456,
    "Tcorroftrrank": 291,
    "Tcorroorbp": 0.26029087616649527,
    "Tcorroorbprank": 205,
    "Tcorrotovr": 0.14587913944542338,
    "Tcorrotovrrank": 84,
    "Teff": 105.4276566549779,
    "Tefgp": 0.5045413260672116,
    "Tftr": 0.3133514986376022,
    "Tneteff": -6.357139192092134,
    "Tneteffrank": 240,
    "Torbp": 0.28,
    "Tposs": 1311.8,
    "Ttovr": 0.1533991079875659,
    "closses": 3,
    "confplace": 2,
    "cwins": 6,
    "dates": [
        [
            11,
            7
        ],
        [
            11,
            11
        ],
        [
            11,
            17
        ],
        [
            11,
            22
        ],
        [
            11,
            23
        ],
        [
            11,
            25
        ],
        [
            11,
            30
        ],
        [
            12,
            13
        ],
        [
            12,
            20
        ],
        [
            12,
            31
        ],
        [
            1,
            4
        ],
        [
            1,
            7
        ],
        [
            1,
            12
        ],
        [
            1,
            14
        ],
        [
            1,
            19
        ],
        [
            1,
            21
        ],
        [
            1,
            26
        ],
        [
            1,
            28
        ]
    ],
    "geff": [
        [
            63.87921022067364,
            91.67636786961583
        ],
        [
            106.77676537585423,
            76.26178591236827
        ],
        [
            127.96833773087072,
            103.8781163434903
        ],
        [
            90.98786828422878,
            105.55234239444766
        ],
        [
            136.11111111111111,
            92.90072102052135
        ],
        [
            87.23958333333334,
            98.19967266775778
        ],
        [
            106.60426417056682,
            120.14038876889849
        ],
        [
            77.68721344880285,
            130.05780346820808
        ],
        [
            76.92307692307692,
            112.93920803123257
        ],
        [
            95.75721862109606,
            85.55684454756381
        ],
        [
            125.89928057553956,
            86.15819209039549
        ],
        [
            108.69565217391305,
            99.49551569506727
        ],
        [
            103.48308934881373,
            107.43174924165824
        ],
        [
            132.2246455834242,
            106.6414686825054
        ],
        [
            91.46341463414635,
            100.05885815185403
        ],
        [
            104.3338683788122,
            128.2051282051282
        ],
        [
            142.6872770511296,
            124.78235635519442
        ],
        [
            123.0723606168446,
            103.74639769452449
        ]
    ],
    "losses": 9,
    "nOT": [
        0,
        0,
        0,
        0,
        0,
        0,
        0,
        0,
        0,
        0,
        0,
        0,
        1,
        0,
        0,
        0,
        0,
        0
    ],
    "pace": 70.9147115973609,
    "poss": [
        [
            68.88,
            68.72
        ],
        [
            70.24,
            72.12
        ],
        [
            75.8,
            72.2
        ],
        [
            69.24,
            69.16
        ],
        [
            72.0,
            72.12
        ],
        [
            76.8,
            73.32
        ],
        [
            76.92,
            74.08
        ],
        [
            78.52,
            76.12
        ],
        [
            75.4,
            71.72
        ],
        [
            67.88,
            68.96
        ],
        [
            72.28,
            70.8
        ],
        [
            73.6,
            71.36
        ],
        [
            79.24,
            79.12
        ],
        [
            73.36,
            74.08
        ],
        [
            72.16,
            67.96000000000001
        ],
        [
            74.76,
            70.2
        ],
        [
            67.28,
            68.92
        ],
        [
            67.44,
            69.4
        ]
    ],
    "preseason_pace": 69.69001562440772,
    "preseason_pred": -9.196161635763247,
    "preseason_predd": 103.17479343848342,
    "preseason_predo": 93.97863180272017,
    "schedule": [
        "mississippi-state",
        "texas-san-antonio",
        "texas-pan-american",
        "cal-state-bakersfield",
        "alcorn-state",
        "texas-el-paso",
        "texas-pan-american",
        "arizona",
        "oklahoma-state",
        "northwestern-state",
        "incarnate-word",
        "incarnate-word",
        "southeastern-louisiana",
        "new-orleans",
        "lamar",
        "houston-baptist",
        "nicholls-state",
        "mcneese-state"
    ],
    "scores": [
        [
            44,
            63
        ],
        [
            75,
            55
        ],
        [
            97,
            75
        ],
        [
            63,
            73
        ],
        [
            98,
            67
        ],
        [
            67,
            72
        ],
        [
            82,
            89
        ],
        [
            61,
            99
        ],
        [
            58,
            81
        ],
        [
            65,
            59
        ],
        [
            91,
            61
        ],
        [
            80,
            71
        ],
        [
            82,
            85
        ],
        [
            97,
            79
        ],
        [
            66,
            68
        ],
        [
            78,
            90
        ],
        [
            96,
            86
        ],
        [
            83,
            72
        ]
    ],
    "wins": 9
}