{
    "CompRank": 275,
    "CompositeDef": 104.52780499344763,
    "CompositeOff": 95.31328199818857,
    "CompositePace": 69.82557298975775,
    "CompositeRating": -9.214522995259049,
    "HA": [
        "H"
    ],
    "OAst": 12.0,
    "OAvgCompRat": 6.316254700963489,
    "OBlk": 4.0,
    "ODR": 21.0,
    "OFGA": 62.0,
    "OFGA3": 21.0,
    "OFGM": 25.0,
    "OFGM3": 5.0,
    "OFTA": 26.0,
    "OFTM": 19.0,
    "OOR": 14.0,
    "OPF": 21.0,
    "OScore": 74.0,
    "OStl": 13.0,
    "OTO": 19.0,
    "Oastr": 0.11489850631941785,
    "Ocomprank": 112,
    "Ocorrdastr": 0.09529577551128515,
    "Ocorrdeff": 90.53468971385787,
    "Ocorrdeffrank": 71,
    "Ocorrdefgp": 0.39375200418892753,
    "Ocorrdftr": 0.2168752409143615,
    "Ocorrdorbp": 0.26000839431333295,
    "Ocorrdtovr": 0.15969714723395115,
    "Ocorroastr": 0.13114319413402675,
    "Ocorroeff": 96.0307074529514,
    "Ocorroeffrank": 244,
    "Ocorroefgp": 0.4729879306435571,
    "Ocorroftr": 0.44065138465802905,
    "Ocorroorbp": 0.3126462912080312,
    "Ocorrotovr": 0.17536150102425352,
    "Oeff": 94.33962264150944,
    "Oefgp": 0.4435483870967742,
    "Oftr": 0.41935483870967744,
    "Oneteff": 5.496017739093531,
    "Oneteffrank": 139,
    "Oorbp": 0.3888888888888889,
    "Oposs": 78.44,
    "Otovr": 0.20553872782345306,
    "SoR": 56.03354417156857,
    "SoRrank": 20,
    "TAst": 15.0,
    "TBlk": 5.0,
    "TDR": 22.0,
    "TFGA": 52.0,
    "TFGA3": 17.0,
    "TFGM": 26.0,
    "TFGM3": 7.0,
    "TFTA": 35.0,
    "TFTM": 24.0,
    "TOR": 8.0,
    "TPF": 19.0,
    "TScore": 83.0,
    "TStl": 10.0,
    "TTO": 18.0,
    "Tastr": 0.149402390438247,
    "Tcorrdastr": 0.11913486404548757,
    "Tcorrdastrrank": 96,
    "Tcorrdeff": 98.01574158247722,
    "Tcorrdeffrank": 151,
    "Tcorrdefgp": 0.4656198498528895,
    "Tcorrdefgprank": 110,
    "Tcorrdftr": 0.34531671213026616,
    "Tcorrdftrrank": 202,
    "Tcorrdorbp": 0.35143034996160605,
    "Tcorrdorbprank": 291,
    "Tcorrdtovr": 0.19868957638698045,
    "Tcorrdtovrrank": 83,
    "Tcorroastr": 0.20843484244791355,
    "Tcorroastrrank": 7,
    "Tcorroeff": 117.628416896886,
    "Tcorroeffrank": 27,
    "Tcorroefgp": 0.706433275541323,
    "Tcorroefgprank": 3,
    "Tcorroftr": 1.0743126886649754,
    "Tcorroftrrank": 1,
    "Tcorroorbp": 0.296689075283284,
    "Tcorroorbprank": 151,
    "Tcorrotovr": 0.22224248575898736,
    "Tcorrotovrrank": 331,
    "Teff": 107.23514211886304,
    "Tefgp": 0.5673076923076923,
    "Tftr": 0.6730769230769231,
    "Tneteff": 19.612675314408776,
    "Tneteffrank": 49,
    "Torbp": 0.27586206896551724,
    "Tposs": 77.4,
    "Ttovr": 0.21077283372365338,
    "closses": 0,
    "confplace": 1,
    "cwins": 0,
    "dates": [
        [
            11,
            11
        ]
    ],
    "geff": [
        [
            107.23514211886304,
            94.33962264150944
        ]
    ],
    "losses": 0,
    "nOT": [
        0
    ],
    "pace": 73.76961101272678,
    "poss": [
        [
            77.4,
            78.44
        ]
    ],
    "preseason_pace": 69.71736892877095,
    "preseason_pred": -10.005392633384366,
    "preseason_predd": 104.70646242584736,
    "preseason_predo": 94.70106979246299,
    "schedule": [
        "colorado"
    ],
    "scores": [
        [
            83,
            74
        ]
    ],
    "wins": 1
}