{
    "CompRank": 343,
    "CompositeDef": 106.56486239095537,
    "CompositeOff": 88.63430420098047,
    "CompositePace": 71.94226871506332,
    "CompositeRating": -17.930558189974892,
    "HA": [
        "A",
        "A",
        "A",
        "A",
        "A",
        "A",
        "A",
        "A",
        "A",
        "A",
        "A",
        "H"
    ],
    "OAst": 206.0,
    "OAvgCompRat": 6.529294351168407,
    "OBlk": 52.0,
    "ODR": 339.0,
    "OFGA": 670.0,
    "OFGA3": 250.0,
    "OFGM": 312.0,
    "OFGM3": 85.0,
    "OFTA": 281.0,
    "OFTM": 206.0,
    "OOR": 111.0,
    "OPF": 171.0,
    "OScore": 915.0,
    "OStl": 100.0,
    "OTO": 172.0,
    "Oastr": 0.1758219248233246,
    "Ocomprank": 5,
    "Ocorrdastr": 0.13533625278429884,
    "Ocorrdeff": 94.79845984019846,
    "Ocorrdeffrank": 2,
    "Ocorrdefgp": 0.4825743773002005,
    "Ocorrdftr": 0.3022853921635794,
    "Ocorrdorbp": 0.28106646473769953,
    "Ocorrdtovr": 0.17454559056777094,
    "Ocorroastr": 0.1475268182992289,
    "Ocorroeff": 103.62175849425677,
    "Ocorroeffrank": 59,
    "Ocorroefgp": 0.4973687312208525,
    "Ocorroftr": 0.2975209972508363,
    "Ocorroorbp": 0.27854991056808637,
    "Ocorrotovr": 0.14920895400578194,
    "Oeff": 107.06262285874755,
    "Oefgp": 0.5291044776119403,
    "Oftr": 0.41940298507462687,
    "Oneteff": 8.823298654058306,
    "Oneteffrank": 6,
    "Oorbp": 0.3100558659217877,
    "Oposs": 854.64,
    "Otovr": 0.17812021043038814,
    "SoR": 0.0,
    "SoRrank": 205,
    "TAst": 129.0,
    "TBlk": 28.0,
    "TDR": 247.0,
    "TFGA": 710.0,
    "TFGA3": 284.0,
    "TFGM": 254.0,
    "TFGM3": 79.0,
    "TFTA": 171.0,
    "TFTM": 121.0,
    "TOR": 98.0,
    "TPF": 243.0,
    "TScore": 708.0,
    "TStl": 82.0,
    "TTO": 180.0,
    "Tastr": 0.11789004240386021,
    "Tcorrdastr": 0.16681628043669366,
    "Tcorrdastrrank": 335,
    "Tcorrdeff": 104.40158660979887,
    "Tcorrdeffrank": 238,
    "Tcorrdefgp": 0.5323066666516381,
    "Tcorrdefgprank": 286,
    "Tcorrdftr": 0.4437448809905666,
    "Tcorrdftrrank": 352,
    "Tcorrdorbp": 0.2995112836014536,
    "Tcorrdorbprank": 284,
    "Tcorrdtovr": 0.1940613603862653,
    "Tcorrdtovrrank": 37,
    "Tcorroastr": 0.12183098882424108,
    "Tcorroastrrank": 296,
    "Tcorroeff": 87.0283423997756,
    "Tcorroeffrank": 354,
    "Tcorroefgp": 0.4286595414655546,
    "Tcorroefgprank": 351,
    "Tcorroftr": 0.2516099322780134,
    "Tcorroftrrank": 317,
    "Tcorroorbp": 0.21553097479628872,
    "Tcorroorbprank": 313,
    "Tcorrotovr": 0.17355592411462128,
    "Tcorrotovrrank": 264,
    "Teff": 81.63830081638301,
    "Tefgp": 0.41338028169014085,
    "Tftr": 0.24084507042253522,
    "Tneteff": -17.373244210023273,
    "Tneteffrank": 333,
    "Torbp": 0.2242562929061785,
    "Tposs": 867.24,
    "Ttovr": 0.18648211843686543,
    "closses": 2,
    "confplace": 9,
    "cwins": 1,
    "dates": [
        [
            11,
            7
        ],
        [
            11,
            11
        ],
        [
            11,
            13
        ],
        [
            11,
            16
        ],
        [
            11,
            18
        ],
        [
            11,
            20
        ],
        [
            11,
            30
        ],
        [
            12,
            10
        ],
        [
            12,
            14
        ],
        [
            1,
            2
        ],
        [
            1,
            4
        ],
        [
            1,
            7
        ]
    ],
    "geff": [
        [
            96.77419354838709,
            100.38503850385038
        ],
        [
            88.25319537431528,
            96.60421545667448
        ],
        [
            67.0662100456621,
            118.76484560570071
        ],
        [
            81.88824662813101,
            110.38046031000471
        ],
        [
            86.56716417910448,
            96.76487579433852
        ],
        [
            88.79363135333743,
            127.25015518311608
        ],
        [
            74.85875706214689,
            121.47570485902818
        ],
        [
            63.87403446226976,
            128.6549707602339
        ],
        [
            78.78446820483961,
            109.22330097087378
        ],
        [
            77.71338250790305,
            89.67391304347827
        ],
        [
            90.36144578313252,
            115.34025374855825
        ],
        [
            83.81226053639847,
            79.0987535953979
        ]
    ],
    "losses": 11,
    "nOT": [
        0,
        0,
        0,
        0,
        0,
        0,
        0,
        0,
        0,
        0,
        0,
        0
    ],
    "pace": 72.74612905082921,
    "poss": [
        [
            74.4,
            72.72
        ],
        [
            65.72,
            68.32
        ],
        [
            70.08,
            67.36
        ],
        [
            83.04,
            85.16
        ],
        [
            67.0,
            69.24000000000001
        ],
        [
            65.32,
            64.44
        ],
        [
            70.8,
            66.68
        ],
        [
            67.32,
            68.4
        ],
        [
            71.08,
            65.92
        ],
        [
            75.92,
            73.6
        ],
        [
            73.04,
            69.36
        ],
        [
            83.52,
            83.44
        ]
    ],
    "preseason_pace": 68.76652417870422,
    "preseason_pred": -20.132292431759062,
    "preseason_predd": 115.11113708194395,
    "preseason_predo": 94.9788446501849,
    "schedule": [
        "texas-christian",
        "oklahoma",
        "mississippi-state",
        "kent-state",
        "cleveland-state",
        "nebraska",
        "air-force",
        "texas",
        "minnesota",
        "alabama-am",
        "alabama-state",
        "texas-southern"
    ],
    "scores": [
        [
            72,
            73
        ],
        [
            58,
            66
        ],
        [
            47,
            80
        ],
        [
            68,
            94
        ],
        [
            58,
            67
        ],
        [
            58,
            82
        ],
        [
            53,
            81
        ],
        [
            43,
            88
        ],
        [
            56,
            72
        ],
        [
            59,
            66
        ],
        [
            66,
            80
        ],
        [
            70,
            66
        ]
    ],
    "wins": 1
}