{
    "CompRank": 36,
    "CompositeDef": 104.1704820292316,
    "CompositeOff": 124.89993281190469,
    "CompositePace": 69.34104444896307,
    "CompositeRating": 20.729450782673094,
    "HA": [
        "H",
        "H",
        "H",
        "N",
        "N",
        "N",
        "H",
        "A",
        "H",
        "H",
        "H",
        "A",
        "H",
        "H"
    ],
    "OAst": 181.0,
    "OAvgCompRat": 3.14077614097733,
    "OBlk": 51.0,
    "ODR": 291.0,
    "OFGA": 906.0,
    "OFGA3": 311.0,
    "OFGM": 385.0,
    "OFGM3": 102.0,
    "OFTA": 247.0,
    "OFTM": 182.0,
    "OOR": 183.0,
    "OPF": 237.0,
    "OScore": 1054.0,
    "OStl": 93.0,
    "OTO": 161.0,
    "Oastr": 0.13341392222189463,
    "Ocomprank": 62,
    "Ocorrdastr": 0.1464557848852625,
    "Ocorrdeff": 104.39325546708218,
    "Ocorrdeffrank": 21,
    "Ocorrdefgp": 0.5002810376629111,
    "Ocorrdftr": 0.3568330484187565,
    "Ocorrdorbp": 0.29637074695618937,
    "Ocorrdtovr": 0.17329331382980873,
    "Ocorroastr": 0.15168399604802232,
    "Ocorroeff": 109.30014247955664,
    "Ocorroeffrank": 139,
    "Ocorroefgp": 0.5202637728270966,
    "Ocorroftr": 0.3549615926927041,
    "Ocorroorbp": 0.32813761825972304,
    "Ocorrotovr": 0.14502470726084082,
    "Oeff": 106.1772172301245,
    "Oefgp": 0.48123620309050774,
    "Oftr": 0.2726269315673289,
    "Oneteff": 4.906887012474456,
    "Oneteffrank": 66,
    "Oorbp": 0.3446327683615819,
    "Oposs": 992.6800000000001,
    "Otovr": 0.13694202504082742,
    "SoR": 24.972027022255194,
    "SoRrank": 59,
    "TAst": 226.0,
    "TBlk": 71.0,
    "TDR": 348.0,
    "TFGA": 874.0,
    "TFGA3": 335.0,
    "TFGM": 412.0,
    "TFGM3": 119.0,
    "TFTA": 354.0,
    "TFTM": 258.0,
    "TOR": 198.0,
    "TPF": 179.0,
    "TScore": 1201.0,
    "TStl": 93.0,
    "TTO": 160.0,
    "Tastr": 0.1596315759733288,
    "Tcorrdastr": 0.12959646927765897,
    "Tcorrdastrrank": 61,
    "Tcorrdeff": 105.12279947950782,
    "Tcorrdeffrank": 114,
    "Tcorrdefgp": 0.473418560379126,
    "Tcorrdefgprank": 63,
    "Tcorrdftr": 0.2755281459055065,
    "Tcorrdftrrank": 27,
    "Tcorrdorbp": 0.3199909917793007,
    "Tcorrdorbprank": 241,
    "Tcorrdtovr": 0.14152380199383363,
    "Tcorrdtovrrank": 230,
    "Tcorroastr": 0.16079935411489923,
    "Tcorroastrrank": 93,
    "Tcorroeff": 125.6269564373916,
    "Tcorroeffrank": 15,
    "Tcorroefgp": 0.5525177860588473,
    "Tcorroefgprank": 67,
    "Tcorroftr": 0.40844578036598195,
    "Tcorroftrrank": 74,
    "Tcorroorbp": 0.41740768185318006,
    "Tcorroorbprank": 5,
    "Tcorrotovr": 0.11618488767126274,
    "Tcorrotovrrank": 13,
    "Teff": 121.09784625312575,
    "Tefgp": 0.5394736842105263,
    "Tftr": 0.40503432494279173,
    "Tneteff": 20.50415695788378,
    "Tneteffrank": 38,
    "Torbp": 0.4049079754601227,
    "Tposs": 991.76,
    "Ttovr": 0.13448090371167296,
    "closses": 3,
    "confplace": 13,
    "cwins": 0,
    "dates": [
        [
            11,
            3
        ],
        [
            11,
            9
        ],
        [
            11,
            14
        ],
        [
            11,
            24
        ],
        [
            11,
            25
        ],
        [
            11,
            26
        ],
        [
            12,
            2
        ],
        [
            12,
            6
        ],
        [
            12,
            10
        ],
        [
            12,
            19
        ],
        [
            12,
            21
        ],
        [
            1,
            3
        ],
        [
            1,
            7
        ],
        [
            1,
            10
        ]
    ],
    "geff": [
        [
            121.39605462822459,
            106.80379746835443
        ],
        [
            108.69565217391303,
            96.36871508379889
        ],
        [
            130.9192200557103,
            110.71623838162931
        ],
        [
            117.32329084588643,
            106.62824207492794
        ],
        [
            114.92622020431327,
            133.92857142857142
        ],
        [
            131.5028901734104,
            113.31841074426413
        ],
        [
            148.08831448572968,
            117.02127659574468
        ],
        [
            101.42857142857143,
            111.42857142857143
        ],
        [
            127.22980062959077,
            90.00537345513165
        ],
        [
            144.64925755248336,
            72.6517903476907
        ],
        [
            162.18585622443015,
            95.49600912200684
        ],
        [
            97.04251386321626,
            111.07533805537668
        ],
        [
            88.5478158205431,
            101.74418604651163
        ],
        [
            90.69920844327177,
            124.75696694750486
        ]
    ],
    "losses": 5,
    "nOT": [
        0,
        0,
        0,
        0,
        0,
        0,
        0,
        0,
        0,
        0,
        0,
        0,
        0,
        0
    ],
    "pace": 69.89166446527017,
    "poss": [
        [
            79.08,
            75.84
        ],
        [
            71.76,
            71.6
        ],
        [
            71.8,
            73.16
        ],
        [
            69.04,
            69.4
        ],
        [
            70.48,
            71.68
        ],
        [
            69.2,
            71.48
        ],
        [
            74.28,
            75.2
        ],
        [
            70.0,
            70.0
        ],
        [
            76.24,
            74.44
        ],
        [
            78.12,
            77.08
        ],
        [
            68.44,
            70.16
        ],
        [
            64.92,
            62.120000000000005
        ],
        [
            67.76,
            68.8
        ],
        [
            60.64,
            61.72
        ]
    ],
    "preseason_pace": 66.38023448473285,
    "preseason_pred": 21.94090728908477,
    "preseason_predd": 99.04965294132653,
    "preseason_predo": 120.99056023041129,
    "schedule": [
        "texas-pan-american",
        "washington",
        "tarleton-state",
        "creighton",
        "st-johns-ny",
        "san-diego-state",
        "sacramento-state",
        "memphis",
        "norfolk-state",
        "alcorn-state",
        "southern",
        "texas-christian",
        "iowa-state",
        "houston"
    ],
    "scores": [
        [
            96,
            81
        ],
        [
            78,
            69
        ],
        [
            94,
            81
        ],
        [
            81,
            74
        ],
        [
            81,
            96
        ],
        [
            91,
            81
        ],
        [
            110,
            88
        ],
        [
            71,
            78
        ],
        [
            97,
            67
        ],
        [
            113,
            56
        ],
        [
            111,
            67
        ],
        [
            63,
            69
        ],
        [
            60,
            70
        ],
        [
            55,
            77
        ]
    ],
    "wins": 9
}