{
    "CompRank": 200,
    "CompositeDef": 112.22264106875365,
    "CompositeOff": 109.13534027024046,
    "CompositePace": 70.01504253164605,
    "CompositeRating": -3.0873007985131835,
    "HA": [
        "A",
        "A",
        "A",
        "A",
        "A",
        "A",
        "A",
        "A",
        "H",
        "H",
        "A",
        "A",
        "A",
        "A",
        "H",
        "H",
        "A",
        "H",
        "H",
        "A",
        "A",
        "H",
        "A",
        "H",
        "H",
        "A",
        "A",
        "A",
        "A",
        "H",
        "H",
        "N",
        "N"
    ],
    "OAst": 520.0,
    "OAvgCompRat": 0.38279354888807726,
    "OBlk": 118.0,
    "ODR": 714.0,
    "OFGA": 2028.0,
    "OFGA3": 815.0,
    "OFGM": 862.0,
    "OFGM3": 264.0,
    "OFTA": 802.0,
    "OFTM": 575.0,
    "OOR": 428.0,
    "OPF": 549.0,
    "OScore": 2563.0,
    "OStl": 257.0,
    "OTO": 340.0,
    "Oastr": 0.1604502480807682,
    "Ocomprank": 143,
    "Ocorrdastr": 0.14965993985504214,
    "Ocorrdeff": 107.35031415684766,
    "Ocorrdeffrank": 109,
    "Ocorrdefgp": 0.5211140885271462,
    "Ocorrdftr": 0.39008225012021147,
    "Ocorrdorbp": 0.30522665895422496,
    "Ocorrdtovr": 0.1615994595933742,
    "Ocorroastr": 0.14497510387735657,
    "Ocorroeff": 108.94873454069761,
    "Ocorroeffrank": 177,
    "Ocorroefgp": 0.5011846177587732,
    "Ocorroftr": 0.3239805153447142,
    "Ocorroorbp": 0.30487679318478633,
    "Ocorrotovr": 0.14031863357890284,
    "Oeff": 111.78081713827152,
    "Oefgp": 0.490138067061144,
    "Oftr": 0.39546351084812625,
    "Oneteff": 1.5984203838499553,
    "Oneteffrank": 127,
    "Oorbp": 0.33914421553090335,
    "Oposs": 2292.88,
    "Otovr": 0.12495957190320778,
    "SoR": 0.0,
    "SoRrank": 98,
    "TAst": 427.0,
    "TBlk": 124.0,
    "TDR": 834.0,
    "TFGA": 1839.0,
    "TFGA3": 620.0,
    "TFGM": 814.0,
    "TFGM3": 197.0,
    "TFTA": 853.0,
    "TFTM": 634.0,
    "TOR": 389.0,
    "TPF": 456.0,
    "TScore": 2459.0,
    "TStl": 191.0,
    "TTO": 471.0,
    "Tastr": 0.13719668928644868,
    "Tcorrdastr": 0.16386090285184746,
    "Tcorrdastrrank": 300,
    "Tcorrdeff": 112.22264106875365,
    "Tcorrdeffrank": 233,
    "Tcorrdefgp": 0.5033688299241257,
    "Tcorrdefgprank": 140,
    "Tcorrdftr": 0.4306805857198284,
    "Tcorrdftrrank": 330,
    "Tcorrdorbp": 0.3367757279585366,
    "Tcorrdorbprank": 302,
    "Tcorrdtovr": 0.13010674981921053,
    "Tcorrdtovrrank": 287,
    "Tcorroastr": 0.13579380794492943,
    "Tcorroastrrank": 252,
    "Tcorroeff": 109.13534027024046,
    "Tcorroeffrank": 165,
    "Tcorroefgp": 0.4903586601868506,
    "Tcorroefgprank": 256,
    "Tcorroftr": 0.42048924629773415,
    "Tcorroftrrank": 31,
    "Tcorroorbp": 0.35074369872245537,
    "Tcorroorbprank": 56,
    "Tcorrotovr": 0.15850531779697052,
    "Tcorrotovrrank": 275,
    "Teff": 107.084378483835,
    "Tefgp": 0.4961935834692768,
    "Tftr": 0.46383904295812944,
    "Tneteff": -3.0873007985131835,
    "Tneteffrank": 200,
    "Torbp": 0.3526745240253853,
    "Tposs": 2296.32,
    "Ttovr": 0.17539809035794615,
    "closses": 11,
    "confplace": 5,
    "cwins": 13,
    "dates": [
        [
            11,
            3
        ],
        [
            11,
            10
        ],
        [
            11,
            14
        ],
        [
            11,
            18
        ],
        [
            11,
            21
        ],
        [
            11,
            24
        ],
        [
            11,
            26
        ],
        [
            12,
            3
        ],
        [
            12,
            6
        ],
        [
            12,
            8
        ],
        [
            12,
            13
        ],
        [
            12,
            29
        ],
        [
            12,
            31
        ],
        [
            1,
            3
        ],
        [
            1,
            5
        ],
        [
            1,
            10
        ],
        [
            1,
            12
        ],
        [
            1,
            17
        ],
        [
            1,
            19
        ],
        [
            1,
            24
        ],
        [
            1,
            27
        ],
        [
            1,
            31
        ],
        [
            2,
            2
        ],
        [
            2,
            7
        ],
        [
            2,
            9
        ],
        [
            2,
            14
        ],
        [
            2,
            16
        ],
        [
            2,
            21
        ],
        [
            2,
            23
        ],
        [
            2,
            28
        ],
        [
            3,
            2
        ],
        [
            3,
            8
        ],
        [
            3,
            9
        ]
    ],
    "geff": [
        [
            107.79436152570482,
            95.55785123966942
        ],
        [
            80.02207505518763,
            125.13455328310012
        ],
        [
            130.12859767299452,
            98.49906191369605
        ],
        [
            100.5600814663951,
            122.74959083469723
        ],
        [
            99.16492693110646,
            112.85183218268722
        ],
        [
            98.13789632611977,
            101.55466399197591
        ],
        [
            70.70135746606336,
            118.84057971014492
        ],
        [
            102.57913247362252,
            120.85441259134346
        ],
        [
            115.50151975683892,
            132.39875389408098
        ],
        [
            122.73524254821741,
            123.4384295062463
        ],
        [
            86.20689655172413,
            146.3630987581313
        ],
        [
            123.54651162790698,
            99.30915371329878
        ],
        [
            101.82998819362457,
            122.05882352941177
        ],
        [
            105.06798516687269,
            113.08068459657702
        ],
        [
            119.94219653179191,
            102.93288212069938
        ],
        [
            125.08122157244964,
            144.50867052023122
        ],
        [
            115.90375586854461,
            111.50234741784038
        ],
        [
            114.75886112725159,
            126.8882175226586
        ],
        [
            123.5424764019989,
            108.50942318675042
        ],
        [
            90.0,
            122.02380952380952
        ],
        [
            110.43622308117062,
            85.39944903581268
        ],
        [
            113.8433515482696,
            94.17304296645086
        ],
        [
            122.33211868818323,
            109.98964803312629
        ],
        [
            100.31678986272439,
            133.2024677509815
        ],
        [
            98.08500700607193,
            91.46341463414635
        ],
        [
            98.2961992136304,
            98.13384813384813
        ],
        [
            123.88818297331638,
            100.0
        ],
        [
            111.78861788617887,
            102.07015526164462
        ],
        [
            113.97276494967436,
            109.67548076923076
        ],
        [
            98.62241703193489,
            103.83889238514789
        ],
        [
            105.2347544522396,
            112.32876712328768
        ],
        [
            104.46479679450488,
            85.9598853868195
        ],
        [
            108.54092526690391,
            126.02179836512262
        ]
    ],
    "losses": 18,
    "nOT": [
        0,
        0,
        0,
        0,
        0,
        1,
        0,
        0,
        0,
        0,
        0,
        0,
        0,
        0,
        0,
        0,
        0,
        0,
        0,
        0,
        0,
        0,
        0,
        0,
        1,
        0,
        0,
        0,
        0,
        0,
        0,
        0,
        0
    ],
    "pace": 70.01504253164605,
    "poss": [
        [
            72.36,
            77.44
        ],
        [
            72.48,
            74.32
        ],
        [
            65.32,
            63.96000000000001
        ],
        [
            78.56,
            73.32
        ],
        [
            76.64,
            75.32
        ],
        [
            79.48,
            79.76
        ],
        [
            70.72,
            69.0
        ],
        [
            68.24,
            71.16
        ],
        [
            65.8,
            64.2
        ],
        [
            68.44,
            67.24
        ],
        [
            66.12,
            67.64
        ],
        [
            68.8,
            69.48
        ],
        [
            67.75999999999999,
            68.0
        ],
        [
            64.72,
            65.44
        ],
        [
            69.2,
            70.92
        ],
        [
            61.56,
            62.28
        ],
        [
            68.16,
            68.16
        ],
        [
            68.84,
            66.2
        ],
        [
            72.03999999999999,
            70.04
        ],
        [
            70.0,
            67.2
        ],
        [
            72.44,
            72.6
        ],
        [
            65.88,
            67.96
        ],
        [
            76.84,
            77.28
        ],
        [
            75.76,
            71.32
        ],
        [
            85.64,
            85.28
        ],
        [
            61.04,
            62.16
        ],
        [
            62.96000000000001,
            64.0
        ],
        [
            68.88,
            69.56
        ],
        [
            67.56,
            66.56
        ],
        [
            63.879999999999995,
            63.56
        ],
        [
            74.12,
            73.0
        ],
        [
            69.88,
            69.8
        ],
        [
            56.2,
            58.72
        ]
    ],
    "preseason_pace": 70.1435586860497,
    "preseason_pred": -9.582506496305633,
    "preseason_predd": 110.8554229842657,
    "preseason_predo": 101.27291648796007,
    "schedule": [
        "texas-christian",
        "louisiana-state",
        "tulane",
        "pepperdine",
        "fresno-state",
        "mississippi-state",
        "texas-tech",
        "memphis",
        "houston-baptist",
        "incarnate-word",
        "houston",
        "texas-pan-american",
        "texas-am-corpus-christi",
        "northwestern-state",
        "texas-am-commerce",
        "nicholls-state",
        "southeastern-louisiana",
        "stephen-f-austin",
        "lamar",
        "mcneese-state",
        "nicholls-state",
        "northwestern-state",
        "texas-am-commerce",
        "texas-pan-american",
        "texas-am-corpus-christi",
        "houston-baptist",
        "incarnate-word",
        "lamar",
        "stephen-f-austin",
        "mcneese-state",
        "southeastern-louisiana",
        "houston-baptist",
        "texas-am-corpus-christi"
    ],
    "scores": [
        [
            78,
            74
        ],
        [
            58,
            93
        ],
        [
            85,
            63
        ],
        [
            79,
            90
        ],
        [
            76,
            85
        ],
        [
            78,
            81
        ],
        [
            50,
            82
        ],
        [
            70,
            86
        ],
        [
            76,
            85
        ],
        [
            84,
            83
        ],
        [
            57,
            99
        ],
        [
            85,
            69
        ],
        [
            69,
            83
        ],
        [
            68,
            74
        ],
        [
            83,
            73
        ],
        [
            77,
            90
        ],
        [
            79,
            76
        ],
        [
            79,
            84
        ],
        [
            89,
            76
        ],
        [
            63,
            82
        ],
        [
            80,
            62
        ],
        [
            75,
            64
        ],
        [
            94,
            85
        ],
        [
            76,
            95
        ],
        [
            84,
            78
        ],
        [
            60,
            61
        ],
        [
            78,
            64
        ],
        [
            77,
            71
        ],
        [
            77,
            73
        ],
        [
            63,
            66
        ],
        [
            78,
            82
        ],
        [
            73,
            60
        ],
        [
            61,
            74
        ]
    ],
    "wins": 15
}